pwn/__init__.py
pwn/toplevel.py
pwnlib/__init__.py
pwnlib/abi.py
pwnlib/args.py
pwnlib/asm.py
pwnlib/atexception.py
pwnlib/atexit.py
pwnlib/config.py
pwnlib/device.py
pwnlib/dynelf.py
pwnlib/exception.py
pwnlib/filepointer.py
pwnlib/fmtstr.py
pwnlib/gdb.py
pwnlib/gdb_api_bridge.py
pwnlib/gdb_faketerminal.py
pwnlib/lexer.py
pwnlib/libcdb.py
pwnlib/log.py
pwnlib/memleak.py
pwnlib/pep237.py
pwnlib/qemu.py
pwnlib/regsort.py
pwnlib/replacements.py
pwnlib/runner.py
pwnlib/testexample.py
pwnlib/timeout.py
pwnlib/ui.py
pwnlib/update.py
pwnlib/useragents.py
pwnlib/version.py
pwnlib/adb/__init__.py
pwnlib/adb/adb.py
pwnlib/adb/bootimg.py
pwnlib/adb/bootloader.py
pwnlib/adb/protocol.py
pwnlib/commandline/__init__.py
pwnlib/commandline/asm.py
pwnlib/commandline/checksec.py
pwnlib/commandline/common.py
pwnlib/commandline/constgrep.py
pwnlib/commandline/cyclic.py
pwnlib/commandline/debug.py
pwnlib/commandline/disablenx.py
pwnlib/commandline/disasm.py
pwnlib/commandline/elfdiff.py
pwnlib/commandline/elfpatch.py
pwnlib/commandline/errno.py
pwnlib/commandline/hex.py
pwnlib/commandline/libcdb.py
pwnlib/commandline/main.py
pwnlib/commandline/phd.py
pwnlib/commandline/pwnstrip.py
pwnlib/commandline/scramble.py
pwnlib/commandline/shellcraft.py
pwnlib/commandline/template.py
pwnlib/commandline/unhex.py
pwnlib/commandline/update.py
pwnlib/commandline/version.py
pwnlib/constants/__init__.py
pwnlib/constants/constant.py
pwnlib/constants/freebsd.py
pwnlib/constants/cgc/__init__.py
pwnlib/constants/cgc/aarch64.py
pwnlib/constants/cgc/alpha.py
pwnlib/constants/cgc/amd64.py
pwnlib/constants/cgc/arm.py
pwnlib/constants/cgc/i386.py
pwnlib/constants/cgc/ia64.py
pwnlib/constants/cgc/mips.py
pwnlib/constants/cgc/powerpc.py
pwnlib/constants/cgc/powerpc64.py
pwnlib/constants/cgc/s390.py
pwnlib/constants/cgc/s390x.py
pwnlib/constants/cgc/sparc.py
pwnlib/constants/cgc/sparc64.py
pwnlib/constants/cgc/thumb.py
pwnlib/constants/linux/__init__.py
pwnlib/constants/linux/aarch64.py
pwntools_elf_only-4.12.0.dev0.dist-info/LICENSE-pwntools.txt
pwntools_elf_only-4.12.0.dev0.dist-info/METADATA
pwntools_elf_only-4.12.0.dev0.dist-info/WHEEL
pwntools_elf_only-4.12.0.dev0.dist-info/entry_points.txt
pwntools_elf_only-4.12.0.dev0.dist-info/top_level.txt
pwntools_elf_only-4.12.0.dev0.dist-info/RECORD
