Metadata-Version: 2.1
Name: pwntools-elf-only
Version: 4.12.0.dev0
Summary: Pwntools CTF framework and exploit development library.
Author-email: "Gallopsled et al." <pwntools-users@googlegroups.com>
License: Mostly MIT, some GPL/BSD, see LICENSE-pwntools.txt
Project-URL: homepage, https://pwntools.com
Project-URL: download, https://github.com/Gallopsled/pwntools/releases
Keywords: pwntools,exploit,ctf,capture,the,flag,binary,wargame,overflow,stack,heap,defcon
Classifier: Development Status :: 5 - Production/Stable
Classifier: Environment :: Console
Classifier: Intended Audience :: Developers
Classifier: Intended Audience :: Science/Research
Classifier: Intended Audience :: System Administrators
Classifier: License :: OSI Approved :: MIT License
Classifier: Natural Language :: English
Classifier: Operating System :: POSIX :: Linux
Classifier: Programming Language :: Python :: 2.7
Classifier: Programming Language :: Python :: 3
Classifier: Topic :: Security
Classifier: Topic :: Software Development :: Assemblers
Classifier: Topic :: Software Development :: Debuggers
Classifier: Topic :: Software Development :: Disassemblers
Classifier: Topic :: Software Development :: Embedded Systems
Classifier: Topic :: Software Development :: Libraries :: Python Modules
Classifier: Topic :: System :: System Shells
Classifier: Topic :: Utilities
Requires-Python: >=3.7
License-File: LICENSE-pwntools.txt
Requires-Dist: mako >=1.0.0
Requires-Dist: pyelftools >=0.2.4
Requires-Dist: ropgadget >=5.3
Requires-Dist: pyserial >=2.7
Requires-Dist: requests >=2.0
Requires-Dist: pip >=6.0.8
Requires-Dist: pygments >=2.0
Requires-Dist: python-dateutil
Requires-Dist: packaging
Requires-Dist: psutil >=3.3.0
Requires-Dist: intervaltree >=3.0
Requires-Dist: sortedcontainers
Requires-Dist: six >=1.12.0
Requires-Dist: rpyc
Requires-Dist: colored-traceback
Requires-Dist: unix-ar
Requires-Dist: zstandard
